arch_blueprint/__init__.py
arch_blueprint/__main__.py
arch_blueprint/blueprint.py
arch_blueprint/modules.py
arch_blueprint/puml.py
arch_blueprint-0.1.5.dist-info/METADATA
arch_blueprint-0.1.5.dist-info/WHEEL
arch_blueprint-0.1.5.dist-info/entry_points.txt
arch_blueprint-0.1.5.dist-info/RECORD
