Metadata-Version: 2.4
Name: arch-blueprint
Version: 0.1.5
Summary: Render your project components automatically in plantuml
Project-URL: Homepage, https://github.com/nkhitrov/arch-blueprint
Project-URL: Repository, https://github.com/nkhitrov/arch-blueprint
Author-email: Nick Khitrov <khitrov34@gmail.com>
Keywords: architecture,diagrams,graphs,plantuml
Classifier: Topic :: Multimedia :: Graphics
Classifier: Topic :: Utilities
Requires-Python: >=3.9
Requires-Dist: grimp>=3.13
